payments_redsys/__init__.py
payments_redsys/test_redsys.py
django_payments_redsys_txels-0.6.0.dist-info/LICENSE
django_payments_redsys_txels-0.6.0.dist-info/METADATA
django_payments_redsys_txels-0.6.0.dist-info/WHEEL
django_payments_redsys_txels-0.6.0.dist-info/RECORD
