Metadata-Version: 2.3
Name: django-payments-redsys-txels
Version: 0.6.0
Summary: A django-payments backend for the Redsys payment gateway
License: MIT
Keywords: django,payments,redsys
Author: AJ Ostergaard
Author-email: aj.ostergaard@gmail.com
Maintainer: Carles Barrobés
Maintainer-email: carles@barrobes.com
Requires-Python: >=3.9
Classifier: Environment :: Web Environment
Classifier: Framework :: Django
Classifier: Intended Audience :: Developers
Classifier: License :: OSI Approved :: MIT License
Classifier: Operating System :: OS Independent
Classifier: Programming Language :: Python :: 3
Classifier: Programming Language :: Python :: 3.9
Classifier: Programming Language :: Python :: 3.10
Classifier: Programming Language :: Python :: 3.11
Classifier: Programming Language :: Python :: 3.12
Classifier: Programming Language :: Python :: 3.13
Classifier: Topic :: Software Development :: Libraries :: Application Frameworks
Classifier: Topic :: Software Development :: Libraries :: Python Modules
Requires-Dist: django (>=4.2.0)
Requires-Dist: django-payments (>=3.0.1)
Requires-Dist: pydes (>=2.0.1,<2.1.0)
Project-URL: Homepage, https://github.com/ajostergaard/django-payments-redsys
Project-URL: Repository, https://github.com/ajostergaard/django-payments-redsys
